Workbook

Sheet Instrucciones
A1: MALE'DENIM OS — Plantilla de Producción (Fase 1)
A4: Hojas conectadas con fórmulas para mostrar la mecánica del módulo.
A6: 1) Órdenes de Ingreso | B6: Transcribe la hoja de la textilera, un renglón por rollo. Columnas grises (código/barcode) las genera el sistema.
A7: 2) Inventario | B7: Se arma solo: unifica por nombre de tela, cuenta rollos y muestra metros disponibles (recibidos − cortados). Desplegable para ver una tela.
A8: 3) Cortes | B8: Eliges la tela POR NOMBRE (desplegable) y los metros; el Inventario se descuenta solo.
A9: 4) Precosteo (formato) | B9: Espejo de tu formato 14500-1: líneas por categoría con IVA, costo total y precio sugerido. Al firmar se archiva en Histórico y se limpia.
A10: 5) Histórico Precosteo | B10: Donde quedan archivados los precosteos firmados (lo llena el botón Guardar y firmar).
A11: 6) Orden de Corte (formato) | B11: Documento que da luz verde al cortador.
A13: Colores
A14: Encabezado azul | B14: Lo llenas tú.
A15: Encabezado gris | B15: Lo llena el sistema.
A16: Texto azul | B16: Ejemplos — bórralos.
A18: Guardar y limpiar (reset a 0) | B18: En Google Sheets se activa con el script Apps Script adjunto: archiva el formato en Histórico y deja los campos en 0. En el módulo es automático.

Sheet Órdenes de Ingreso
A1: textilera | B1: numero_documento | C1: tipo_documento | D1: fecha | E1: orden_compra | F1: numero_rollo | G1: serial | H1: lote_fabrica | I1: tono | J1: referencia_tela | K1: descripcion_tela | L1: ancho_cm | M1: metros | N1: costo_metro_cop | O1: codigo_interno | P1: barcode
A2: Primatela | B2: 7572901088 | C2: remision | D2: 2025-10-29 | E2: OC-1042 | F2: 6000321268 | H2: 0001319184 | J2: SANDDENIM-0009 | K2: SANDDENIM | L2: 150 | M2: 47.9 | N2: 9800
A3: Primatela | B3: 7572901088 | C3: remision | D3: 2025-10-29 | E3: OC-1042 | F3: 6000321251 | H3: 0001319184 | J3: SANDDENIM-0009 | K3: SANDDENIM | L3: 150 | M3: 51.1 | N3: 9800
A4: Contacto | B4: 30-10002 | C4: lista_empaque | D4: 2026-06-19 | E4: PF-4250 | F4: 654 | G4: 53242 | H4: 1 | I4: A | J4: 922020175 | K4: FUNKY | L4: 150 | M4: 82 | N4: 12500
A5: Contacto | B5: 30-10002 | C5: lista_empaque | D5: 2026-06-19 | E5: PF-4250 | F5: 492 | G5: 53080 | H5: 1 | I5: A | J5: 922020175 | K5: FUNKY | L5: 150 | M5: 80.1 | N5: 12500
A6: Megatex | B6: FEMT16043 | C6: factura | D6: 2026-02-12 | E6: 0000 | F6: TOTAL | J6: 2600772 | K6: BRUSELAS INDIGO 9.8oz | L6: 150 | M6: 307.7 | N6: 16000

Sheet Inventario
A1: INVENTARIO DE TELA — unificado por nombre
A3: Ver tela: | B3: SANDDENIM | C3: Rollos: | D3: =IFERROR(VLOOKUP(B3,$A$7:$E$20,2,0),0) -> 2 | E3: =IFERROR("Disponible: "&TEXT(VLOOKUP(B3,$A$7:$E$20,5,0),"#,##0.0")&" m","") -> Disponible: 69.0 m
A6: nombre_tela | B6: nro_rollos | C6: metros_recibidos | D6: metros_cortados | E6: metros_disponibles
A7: SANDDENIM | B7: =IF($A7="","",COUNTIF('Órdenes de Ingreso'!$K:$K,$A7)) -> 2 | C7: =IF($A7="","",SUMIF('Órdenes de Ingreso'!$K:$K,$A7,'Órdenes de Ingreso'!$M:$M)) -> 99 | D7: =IF($A7="","",SUMIF(Cortes!$B:$B,$A7,Cortes!$D:$D)) -> 30 | E7: =IF($A7="","",$C7-$D7) -> 69
A8: FUNKY | B8: =IF($A8="","",COUNTIF('Órdenes de Ingreso'!$K:$K,$A8)) -> 2 | C8: =IF($A8="","",SUMIF('Órdenes de Ingreso'!$K:$K,$A8,'Órdenes de Ingreso'!$M:$M)) -> 162.1 | D8: =IF($A8="","",SUMIF(Cortes!$B:$B,$A8,Cortes!$D:$D)) -> 0 | E8: =IF($A8="","",$C8-$D8) -> 162.1
A9: BRUSELAS INDIGO 9.8oz | B9: =IF($A9="","",COUNTIF('Órdenes de Ingreso'!$K:$K,$A9)) -> 1 | C9: =IF($A9="","",SUMIF('Órdenes de Ingreso'!$K:$K,$A9,'Órdenes de Ingreso'!$M:$M)) -> 307.7 | D9: =IF($A9="","",SUMIF(Cortes!$B:$B,$A9,Cortes!$D:$D)) -> 0 | E9: =IF($A9="","",$C9-$D9) -> 307.7
B10: =IF($A10="","",COUNTIF('Órdenes de Ingreso'!$K:$K,$A10)) | C10: =IF($A10="","",SUMIF('Órdenes de Ingreso'!$K:$K,$A10,'Órdenes de Ingreso'!$M:$M)) | D10: =IF($A10="","",SUMIF(Cortes!$B:$B,$A10,Cortes!$D:$D)) | E10: =IF($A10="","",$C10-$D10)
B11: =IF($A11="","",COUNTIF('Órdenes de Ingreso'!$K:$K,$A11)) | C11: =IF($A11="","",SUMIF('Órdenes de Ingreso'!$K:$K,$A11,'Órdenes de Ingreso'!$M:$M)) | D11: =IF($A11="","",SUMIF(Cortes!$B:$B,$A11,Cortes!$D:$D)) | E11: =IF($A11="","",$C11-$D11)

Sheet Cortes
A1: fecha | B1: tela_nombre | C1: referencia_prenda | D1: metros_usados | E1: tono | F1: responsable
A2: 2026-06-26 | B2: SANDDENIM | C2: REF 14500-1 | D2: 30 | F2: Cortador 1

Sheet Precosteo (formato)
A1: PRECOSTEO · MALE'DENIM OS
A2: REF | B2: 14500-1 | C2: NOMBRE | D2: SKINNY OSCURO | F2: FOTO (link)
A3: TELA | B3: VERBENA | C3: COLOR | D3: OSCURO | F3: IVA % | G3: 0.19
A5: CATEGORIA | B5: ITEM | C5: VALOR UNITARIO | D5: CANTIDAD | E5: IVA | F5: TOTAL SIN IVA | G5: TOTAL CON IVA
A6: DIRTY JEANS | B6: PRECIO TELA | C6: 15900 | D6: 1 | E6: =ROUND(F6*$G$3,0) -> 3021 | F6: =C6*D6 -> 15900 | G6: =F6+E6 -> 18921
B7: PRECIO COMPLEMENTO | C7: 0 | D7: 1 | E7: =ROUND(F7*$G$3,0) -> 0 | F7: =C7*D7 -> 0 | G7: =F7+E7 -> 0
A8: MP | B8: TELA | C8: 15900 | D8: 1.07 | E8: =ROUND(F8*$G$3,0) -> 3232 | F8: =C8*D8 -> 17013 | G8: =F8+E8 -> 20245
B9: FORRO | C9: 4400 | D9: 0.15 | E9: =ROUND(F9*$G$3,0) -> 125 | F9: =C9*D9 -> 660 | G9: =F9+E9 -> 785
B10: COMPLEMENTO | C10: 0 | D10: 1 | E10: =ROUND(F10*$G$3,0) -> 0 | F10: =C10*D10 -> 0 | G10: =F10+E10 -> 0
A11: PROCESO EN MP | B11: BORDADO | C11: 0 | D11: 1 | E11: =ROUND(F11*$G$3,0) -> 0 | F11: =C11*D11 -> 0 | G11: =F11+E11 -> 0
B12: CORE | C12: 1200 | D12: 1 | E12: =ROUND(F12*$G$3,0) -> 228 | F12: =C12*D12 -> 1200 | G12: =F12+E12 -> 1428
A13: PROCESO | B13: CONFECCION | C13: 10700 | D13: 1 | E13: =ROUND(F13*$G$3,0) -> 2033 | F13: =C13*D13 -> 10700 | G13: =F13+E13 -> 12733
A14: INSUMO CONFECCION | B14: CIERRE | C14: 700 | D14: 1 | E14: =ROUND(F14*$G$3,0) -> 133 | F14: =C14*D14 -> 700 | G14: =F14+E14 -> 833
B15: MARQUILLA TALLA | C15: 87 | D15: 1 | E15: =ROUND(F15*$G$3,0) -> 17 | F15: =C15*D15 -> 87 | G15: =F15+E15 -> 104
B16: BANDERA COLOMBIA | C16: 0 | D16: 0.07 | E16: =ROUND(F16*$G$3,0) -> 0 | F16: =C16*D16 -> 0 | G16: =F16+E16 -> 0
A17: PROCESO | B17: LAVANDERIA | C17: 7000 | D17: 1 | E17: =ROUND(F17*$G$3,0) -> 1330 | F17: =C17*D17 -> 7000 | G17: =F17+E17 -> 8330
B18: TERMINACION | C18: 2100 | D18: 1 | E18: =ROUND(F18*$G$3,0) -> 399 | F18: =C18*D18 -> 2100 | G18: =F18+E18 -> 2499
A19: INSUMO EMPAQUE | B19: CODIGO | C19: 20 | D19: 1 | E19: =ROUND(F19*$G$3,0) -> 4 | F19: =C19*D19 -> 20 | G19: =F19+E19 -> 24
B20: PRETINERA | C20: 123 | D20: 1 | E20: =ROUND(F20*$G$3,0) -> 23 | F20: =C20*D20 -> 123 | G20: =F20+E20 -> 146
B21: INSTRUCCION LAVADO IMPRESA | C21: 10 | D21: 1 | E21: =ROUND(F21*$G$3,0) -> 2 | F21: =C21*D21 -> 10 | G21: =F21+E21 -> 12
B22: EMPAQUE | C22: 180 | D22: 1 | E22: =ROUND(F22*$G$3,0) -> 34 | F22: =C22*D22 -> 180 | G22: =F22+E22 -> 214
A23: INSUMO TERMINACION | B23: BOTON 27 L PASTA | C23: 278 | D23: 1 | E23: =ROUND(F23*$G$3,0) -> 53 | F23: =C23*D23 -> 278 | G23: =F23+E23 -> 331
B24: REMACHE | C24: 111 | D24: 2 | E24: =ROUND(F24*$G$3,0) -> 42 | F24: =C24*D24 -> 222 | G24: =F24+E24 -> 264
B25: GARRA | C25: 700 | D25: 1 | E25: =ROUND(F25*$G$3,0) -> 133 | F25: =C25*D25 -> 700 | G25: =F25+E25 -> 833
B26: APLIQUES PROFINTEX | C26: 0 | D26: 1 | E26: =ROUND(F26*$G$3,0) -> 0 | F26: =C26*D26 -> 0 | G26: =F26+E26 -> 0
B27: ENTRETELA | C27: 0 | D27: 1 | E27: =ROUND(F27*$G$3,0) -> 0 | F27: =C27*D27 -> 0 | G27: =F27+E27 -> 0
A28: GASTOS FIJOS | B28: GASTOS FIJOS | C28: 11000 | D28: 1 | E28: =ROUND(F28*$G$3,0) -> 2090 | F28: =C28*D28 -> 11000 | G28: =F28+E28 -> 13090
B29: COSTO TOTAL | F29: =SUM(F6:F28) -> 67893 | G29: =SUM(G6:G28) -> 80792
A31: PRECIO SUGERIDO DE VENTA (CON IVA)
A32: Costo base (sin IVA) | B32: =F29 -> 67893
A33: Margen % | B33: PRECIO VENTA (con IVA) | C33: Precio antes de IVA | D33: IVA 19% | E33: Margen real %
A34: 0.5 | B34: =ROUND($B$32*(1+A34)*(1+$G$3),0) -> 121189 | C34: =ROUND(B34/(1+$G$3),0) -> 101839 | D34: =B34-C34 -> 19350 | E34: =IF(C34=0,0,(C34-$B$32)/C34) -> 0.33333006
A35: 0.65 | B35: =ROUND($B$32*(1+A35)*(1+$G$3),0) -> 133308 | C35: =ROUND(B35/(1+$G$3),0) -> 112024 | D35: =B35-C35 -> 21284 | E35: =IF(C35=0,0,(C35-$B$32)/C35) -> 0.39394237
A36: 0.8 | B36: =ROUND($B$32*(1+A36)*(1+$G$3),0) -> 145427 | C36: =ROUND(B36/(1+$G$3),0) -> 122208 | D36: =B36-C36 -> 23219 | E36: =IF(C36=0,0,(C36-$B$32)/C36) -> 0.44444717
A38: ESTADO | C38: AUTORIZADO POR | F38: FECHA
A40: ▶ Botón 'Guardar y firmar' (Apps Script): archiva en 'Histórico Precosteo' y limpia el formato a 0.

Sheet Histórico Precosteo
A1: fecha_firma | B1: ref | C1: nombre | D1: tela | E1: color | F1: costo_total_sin_iva | G1: costo_total_con_iva | H1: precio_sugerido | I1: autorizado_por
A2: (las filas firmadas se agregan aquí automáticamente)

Sheet Orden de Corte (formato)
A1: ORDEN DE CORTE · MALE'DENIM OS
A2: Documento que autoriza al cortador a iniciar (luz verde)
A4: Consecutivo | C4: Fecha
A5: Referencia (prenda) | C5: Tono
A6: Tela (nombre) | B6: SANDDENIM | C6: Disponible (m) | D6: =IFERROR(VLOOKUP(B6,Inventario!$A$7:$E$20,5,0),0) -> 69
A7: Responsable | C7: Fecha límite
A9: ROLLOS ASIGNADOS
A10: codigo_interno | B10: numero_rollo | C10: lote_fabrica | D10: tono | E10: metros_usados
A16: TRAZO Y TENDIDO
A17: Largo trazo (m) | C17: Nº capas
A18: Prendas por trazo | C18: Prendas estimadas
A19: Rend. teórico (m/prenda) | C19: Consumo real
A20: Diferencia % | C20: Merma (% o m)
A22: CURVA DE TALLAS
A23: 4 | B23: 6 | C23: 8 | D23: 10 | E23: 12 | F23: 14 | G23: 16
A26: INDICACIONES AL CORTADOR
A27: (Sentido de la tela, defectos a evitar, notas de calidad, etc.)
A31: AUTORIZADO POR (firma) | D31: Estado
